trulens/instrument/langchain/__init__.py
trulens/instrument/langchain/guardrails.py
trulens/instrument/langchain/langchain.py
trulens/instrument/langchain/py.typed
trulens/instrument/langchain/tru_chain.py
trulens_instrument_langchain-1.0.1a1.dist-info/METADATA
trulens_instrument_langchain-1.0.1a1.dist-info/WHEEL
trulens_instrument_langchain-1.0.1a1.dist-info/RECORD
