Metadata-Version: 2.1
Name: trulens-instrument-langchain
Version: 1.0.1a1
Summary: Library to systematically track and evaluate LLM based applications.
Home-page: https://trulens.org/
License: MIT
Author: Snowflake Inc.
Author-email: ml-observability-wg-dl@snowflake.com
Requires-Python: >=3.9,<3.13
Classifier: Development Status :: 3 - Alpha
Classifier: License :: OSI Approved :: MIT License
Classifier: Operating System :: OS Independent
Classifier: Programming Language :: Python :: 3
Classifier: Programming Language :: Python :: 3.9
Classifier: Programming Language :: Python :: 3.10
Classifier: Programming Language :: Python :: 3.11
Classifier: Programming Language :: Python :: 3.12
Requires-Dist: langchain (>=0.2.10,<0.3.0,!=0.2.12)
Requires-Dist: langchain-core (>=0.2.24,<0.3.0,!=0.2.27)
Requires-Dist: pydantic (>=2,<3)
Requires-Dist: trulens-core (>=1.0.0,<2.0.0)
Requires-Dist: typing-inspect (>=0.8,<0.9)
Project-URL: Documentation, https://trulens.org/trulens/getting_started/
Project-URL: Repository, https://github.com/truera/trulens
